README
require_python_3.py
setup.py
require_python_3.egg-info/PKG-INFO
require_python_3.egg-info/SOURCES.txt
require_python_3.egg-info/dependency_links.txt
require_python_3.egg-info/top_level.txt