Metadata-Version: 1.1
Name: require-python-3
Version: 1
Summary: Makes your script require python 3
Home-page: https://github.com/asperous/require-python-3
Author: Andrew Chase
Author-email: theandychase@gmail.com
License: MIT
Platform: UNKNOWN
Classifier: Programming Language :: Python :: 2
Classifier: Programming Language :: Python :: 3
Classifier: Intended Audience :: Developers
Classifier: License :: OSI Approved :: MIT License
Classifier: Topic :: Software Development :: Libraries
Classifier: Topic :: Utilities
